setup.py
chikka/__init__.py
chikka/core.py
chikka/exceptions.py
python_chikka.egg-info/PKG-INFO
python_chikka.egg-info/SOURCES.txt
python_chikka.egg-info/dependency_links.txt
python_chikka.egg-info/requires.txt
python_chikka.egg-info/top_level.txt