Metadata-Version: 1.1
Name: python-chikka
Version: 0.1
Summary: Python API Wrapper for Chikka 
Home-page: https://github.com/makmac213/python-chikka/
Author: Mark Allan B Meriales
Author-email: mark.meriales@gmail.com
License: UNKNOWN
Download-URL: https://github.com/makmac213/python-chikka/
Platform: UNKNOWN
Classifier: Development Status :: 4 - Beta
Classifier: Intended Audience :: Developers
Classifier: Natural Language :: English
Classifier: Programming Language :: Python
Classifier: License :: Freeware
